schedule/__init__.py
schedule/job.py
schedule/schedule.py
schedule/store.py
schedule/trigger.py
schedule/utils.py
cron_schedule-1.1.dist-info/WHEEL
cron_schedule-1.1.dist-info/METADATA
cron_schedule-1.1.dist-info/RECORD
