Metadata-Version: 2.1
Name: cron-schedule
Version: 1.1
Summary: 基于cron表达式的定时任务
Keywords: cron,定时任务,schedule
Author: miclon
Author-email: jcnd@163.com
Requires-Python: >=3.8,<4.0
Classifier: Programming Language :: Python :: 3
Classifier: Programming Language :: Python :: 3.10
Classifier: Programming Language :: Python :: 3.8
Classifier: Programming Language :: Python :: 3.9
Requires-Dist: croniter (>=1.3.7,<2.0.0)
